Myfreegpt/__init__.py
Myfreegpt/AsyncClient/__init__.py
Myfreegpt/AsyncClient/alpaca_7b.py
Myfreegpt/AsyncClient/falcon_40b.py
Myfreegpt/AsyncClient/gpt3.py
Myfreegpt/AsyncClient/gpt4.py
Myfreegpt/AsyncClient/pollinations.py
Myfreegpt/AsyncClient/prodia.py
Myfreegpt/Client/__init__.py
Myfreegpt/Client/alpaca_7b.py
Myfreegpt/Client/falcon_40b.py
Myfreegpt/Client/gpt3.py
Myfreegpt/Client/gpt4.py
Myfreegpt/Client/pollinations.py
Myfreegpt/Client/prodia.py
Myfreegpt-1.1.1.dist-info/LICENSE
Myfreegpt-1.1.1.dist-info/METADATA
Myfreegpt-1.1.1.dist-info/WHEEL
Myfreegpt-1.1.1.dist-info/top_level.txt
Myfreegpt-1.1.1.dist-info/RECORD
