Metadata-Version: 2.1
Name: Myfreegpt
Version: 1.1.1
Summary: This is my first module
Home-page: 
Author: irfirf123
Author-email: hack-mr2016@yandex.ru
Classifier: Programming Language :: Python :: 3.11
Classifier: License :: OSI Approved :: MIT License
Classifier: Operating System :: OS Independent
Requires-Python: >=3.7
License-File: LICENSE
Requires-Dist: requests >=2.25.1
